{"openapi":"3.0.1","info":{"title":"OpenAPI definition","version":"v0"},"servers":[{"url":"http://localhost:8080","description":"Generated server url"}],"paths":{"/api/sensores":{"get":{"tags":["sensor-controller"],"operationId":"getAllSensores","responses":{"200":{"description":"OK","content":{"*/*":{"schema":{"type":"array","items":{"$ref":"#/components/schemas/Sensor"}}}}}}},"post":{"tags":["sensor-controller"],"operationId":"createSensor","requestBody":{"content":{"application/json":{"schema":{"$ref":"#/components/schemas/Sensor"}}},"required":true},"responses":{"200":{"description":"OK","content":{"*/*":{"schema":{"$ref":"#/components/schemas/Sensor"}}}}}}},"/api/sensores/{id}/leituras":{"get":{"tags":["sensor-controller"],"operationId":"getLeiturasDoSensor","parameters":[{"name":"id","in":"path","required":true,"schema":{"type":"string"}}],"responses":{"200":{"description":"OK","content":{"*/*":{"schema":{"type":"array","items":{"$ref":"#/components/schemas/SensorData"}}}}}}}}},"components":{"schemas":{"Sensor":{"type":"object","properties":{"id":{"type":"string"},"tipo":{"type":"string"},"divisao":{"type":"string"},"unidade":{"type":"string"},"leituras":{"type":"array","items":{"$ref":"#/components/schemas/SensorData"}}}},"SensorData":{"type":"object","properties":{"id":{"type":"integer","format":"int64"},"sensor":{"$ref":"#/components/schemas/Sensor"},"valor":{"type":"number","format":"double"},"timestamp":{"type":"string","format":"date-time"}}}}}}